[{"farmer_unique_id":"342289485","site_id":8415,"date":"2021-06-20 08:33:32","filename":"L1094F04268C01S08415Rp26242.jpg","season":"LR2021","growth_stage":"M","damage":"G","extent":0,"drought_probability":0.0009,"drought_extent":-0,"growth_sowing":0.0001,"growth_vegetative":0.0001,"growth_flowering":0.965,"growth_maturity":0.0348,"disturbance_none":0.9955,"disturbance_weeds":0.0044,"disturbance_drought":0.0001,"disturbance_nutrient_deficit":0.0001,"crop_name":"maize","spatial_location":"Kanduyi"}]
