[{"farmer_unique_id":"345239230","site_id":8980,"date":"2021-07-29 16:26:11","filename":"L1094F04274C01S08980Rp31831.jpg","season":"LR2021","growth_stage":"M","damage":"WD","extent":10,"drought_probability":0.7232,"drought_extent":17,"growth_sowing":4.4039e-06,"growth_vegetative":0.0005,"growth_flowering":0.4307,"growth_maturity":0.5687,"disturbance_none":0.1223,"disturbance_weeds":0.2394,"disturbance_drought":0.6318,"disturbance_nutrient_deficit":0.0065,"crop_name":"maize","spatial_location":"Kanduyi"}]
