[{"farmer_unique_id":"1104221","site_id":7973,"date":"2021-07-02 17:48:47","filename":"L1094F00509C01S07973Rp29207.jpg","season":"LR2021","growth_stage":"F","damage":"WD","extent":10,"drought_probability":0.0484,"drought_extent":48,"growth_sowing":0.0006,"growth_vegetative":0.1292,"growth_flowering":0.8573,"growth_maturity":0.013,"disturbance_none":0.1249,"disturbance_weeds":0.8679,"disturbance_drought":0.0048,"disturbance_nutrient_deficit":0.0023,"crop_name":"maize","spatial_location":"Bumula"}]
