[{"farmer_unique_id":"744678","site_id":9083,"date":"2021-06-25 09:30:18","filename":"L1115F00400C01S09083Rp27517.jpg","season":"LR2021","growth_stage":"V","damage":"G","extent":0,"drought_probability":0.0064,"drought_extent":0,"growth_sowing":0.0005,"growth_vegetative":0.0007,"growth_flowering":0.9924,"growth_maturity":0.0064,"disturbance_none":0.99,"disturbance_weeds":0.0099,"disturbance_drought":0.0001,"disturbance_nutrient_deficit":9.9746e-06,"crop_name":"maize","spatial_location":"Tongaren"}]
