[{"farmer_unique_id":"1759407","site_id":8528,"date":"2021-07-15 10:46:15","filename":"L1116F01107C01S08528Rp30779.jpg","season":"LR2021","growth_stage":"F","damage":"WD","extent":20,"drought_probability":0.3729,"drought_extent":1,"growth_sowing":0.001,"growth_vegetative":0.0004,"growth_flowering":0.4667,"growth_maturity":0.5319,"disturbance_none":0.3262,"disturbance_weeds":0.544,"disturbance_drought":0.1216,"disturbance_nutrient_deficit":0.0083,"crop_name":"maize","spatial_location":"Tongaren"}]
