[{"farmer_unique_id":"3513248","site_id":9084,"date":"2021-08-09 13:14:06","filename":"L1115F02203C01S09084Rp32198.jpg","season":"LR2021","growth_stage":"M","damage":"G","extent":0,"drought_probability":0.9347,"drought_extent":22,"growth_sowing":0.0004,"growth_vegetative":0.0003,"growth_flowering":0.0915,"growth_maturity":0.9078,"disturbance_none":0.0131,"disturbance_weeds":0.0104,"disturbance_drought":0.9638,"disturbance_nutrient_deficit":0.0128,"crop_name":"maize","spatial_location":"Tongaren"}]
