[{"farmer_unique_id":"2892740","site_id":9378,"date":"2021-05-07 15:56:15","filename":"L1125F01747C01S09378Rp17769.jpg","season":"LR2021","growth_stage":"V","damage":"WD","extent":20,"drought_probability":0.1341,"drought_extent":6,"growth_sowing":0.0101,"growth_vegetative":0.9595,"growth_flowering":0.0299,"growth_maturity":0.0005,"disturbance_none":0.1406,"disturbance_weeds":0.829,"disturbance_drought":0.0303,"disturbance_nutrient_deficit":0.0001,"crop_name":"maize","spatial_location":"Teso-North"}]
