[{"farmer_unique_id":"406467144","site_id":9718,"date":"2021-04-24 08:36:58","filename":"L1122F04428C01S09718Rp16075.jpg","season":"LR2021","growth_stage":"V","damage":"PS","extent":10,"drought_probability":0.0774,"drought_extent":2,"growth_sowing":0.0002,"growth_vegetative":0.1857,"growth_flowering":0.0672,"growth_maturity":0.7469,"disturbance_none":0.4437,"disturbance_weeds":0.2161,"disturbance_drought":0.3379,"disturbance_nutrient_deficit":0.0023,"crop_name":"maize","spatial_location":"Teso-North"}]
