[{"farmer_unique_id":"3378312","site_id":10062,"date":"2021-04-28 15:54:44","filename":"L113F02080C01S10062Rp16503.jpg","season":"LR2021","growth_stage":"V","damage":"G","extent":0,"drought_probability":0.1751,"drought_extent":2,"growth_sowing":0.0012,"growth_vegetative":0.0547,"growth_flowering":0.8263,"growth_maturity":0.1178,"disturbance_none":0.1328,"disturbance_weeds":0.8459,"disturbance_drought":0.0213,"disturbance_nutrient_deficit":0.0001,"crop_name":"maize","spatial_location":"Runyenjes"}]
