[{"farmer_unique_id":"1467559","site_id":8170,"date":"2021-05-16 09:51:45","filename":"L1136F00953C01S08170Rp19239.jpg","season":"LR2021","growth_stage":"V","damage":"G","extent":0,"drought_probability":0.0002,"drought_extent":3,"growth_sowing":0.0002,"growth_vegetative":0.9737,"growth_flowering":0.0258,"growth_maturity":0.0003,"disturbance_none":0.0256,"disturbance_weeds":0.9744,"disturbance_drought":0.0001,"disturbance_nutrient_deficit":4.4763e-06,"crop_name":"maize","spatial_location":"Nambale"}]
