[{"farmer_unique_id":"BS012","site_id":9074,"date":"2021-08-06 10:51:55","filename":"L1136F00047C01S09074Rp32161.jpg","season":"LR2021","growth_stage":"M","damage":"G","extent":0,"drought_probability":0.6282,"drought_extent":66,"growth_sowing":0.0006,"growth_vegetative":0.0026,"growth_flowering":0.0589,"growth_maturity":0.9379,"disturbance_none":0.0463,"disturbance_weeds":0.5741,"disturbance_drought":0.2842,"disturbance_nutrient_deficit":0.0954,"crop_name":"maize","spatial_location":"Matayos"}]
