[{"farmer_unique_id":"358507525","site_id":7514,"date":"2021-06-16 11:39:59","filename":"L1132F04295C01S07514Rp25280.jpg","season":"LR2021","growth_stage":"F","damage":"DR","extent":20,"drought_probability":0.0334,"drought_extent":15,"growth_sowing":0,"growth_vegetative":0.0006,"growth_flowering":0.9505,"growth_maturity":0.0489,"disturbance_none":0.4385,"disturbance_weeds":0.5423,"disturbance_drought":0.0189,"disturbance_nutrient_deficit":0.0003,"crop_name":"maize","spatial_location":"Teso-South"}]
