[{"farmer_unique_id":"416832277","site_id":9223,"date":"2021-07-18 08:39:14","filename":"L1144F04450C01S09223Rp30968.jpg","season":"LR2021","growth_stage":"M","damage":"G","extent":0,"drought_probability":0.7691,"drought_extent":69,"growth_sowing":6.1624e-06,"growth_vegetative":0.0081,"growth_flowering":0.0906,"growth_maturity":0.9013,"disturbance_none":0.001,"disturbance_weeds":0.0076,"disturbance_drought":0.9843,"disturbance_nutrient_deficit":0.0071,"crop_name":"maize","spatial_location":"Butula"}]
