[{"farmer_unique_id":"744863","site_id":8171,"date":"2021-04-25 14:13:07","filename":"L1149F00401C01S08171Rp16218.jpg","season":"LR2021","growth_stage":"V","damage":"G","extent":0,"drought_probability":0.0152,"drought_extent":2,"growth_sowing":0.0009,"growth_vegetative":0.8623,"growth_flowering":0.1158,"growth_maturity":0.0209,"disturbance_none":0.1197,"disturbance_weeds":0.8782,"disturbance_drought":0.0009,"disturbance_nutrient_deficit":0.0012,"crop_name":"maize","spatial_location":"Funyula"}]
