[{"farmer_unique_id":"72898","site_id":8705,"date":"2021-06-10 06:59:21","filename":"L1153F03533C01S08705Rp24064.jpg","season":"LR2021","growth_stage":"M","damage":"WD","extent":20,"drought_probability":0.5535,"drought_extent":1,"growth_sowing":0.0018,"growth_vegetative":0.0079,"growth_flowering":0.1501,"growth_maturity":0.8403,"disturbance_none":0.1884,"disturbance_weeds":0.5595,"disturbance_drought":0.2371,"disturbance_nutrient_deficit":0.015,"crop_name":"maize","spatial_location":"Budalangi"}]
