[{"farmer_unique_id":"366270748","site_id":10878,"date":"2021-05-20 09:22:22","filename":"L1153F04301C01S10878Rp20347.jpg","season":"LR2021","growth_stage":"V","damage":"WD","extent":30,"drought_probability":0.0102,"drought_extent":0,"growth_sowing":0.0023,"growth_vegetative":0.0145,"growth_flowering":0.918,"growth_maturity":0.0653,"disturbance_none":0.0663,"disturbance_weeds":0.9099,"disturbance_drought":0.0025,"disturbance_nutrient_deficit":0.0213,"crop_name":"maize","spatial_location":"Budalangi"}]
