[{"farmer_unique_id":"3262608","site_id":9834,"date":"2021-05-23 07:26:24","filename":"L133F01993C01S09834Rp20846.jpg","season":"LR2021","growth_stage":"V","damage":"WD","extent":20,"drought_probability":0.0095,"drought_extent":1,"growth_sowing":0.0002,"growth_vegetative":0.1636,"growth_flowering":0.8284,"growth_maturity":0.0077,"disturbance_none":0.093,"disturbance_weeds":0.9059,"disturbance_drought":0.001,"disturbance_nutrient_deficit":0.0001,"crop_name":"maize","spatial_location":"Mbeere-South"}]
