[{"farmer_unique_id":"1517271","site_id":7887,"date":"2021-07-08 06:46:44","filename":"L133F00979C01S07887Rp29895.jpg","season":"LR2021","growth_stage":"M","damage":"DR","extent":50,"drought_probability":0.9325,"drought_extent":65,"growth_sowing":0.0001,"growth_vegetative":0.0001,"growth_flowering":0.0185,"growth_maturity":0.9813,"disturbance_none":0.0019,"disturbance_weeds":0.0193,"disturbance_drought":0.9626,"disturbance_nutrient_deficit":0.0162,"crop_name":"maize","spatial_location":"Mbeere-South"}]
