[{"farmer_unique_id":"1332304427","site_id":9589,"date":"2021-06-25 07:59:24","filename":"L133F00696C01S09589Rp27451.jpg","season":"LR2021","growth_stage":"V","damage":"DR","extent":60,"drought_probability":0.2995,"drought_extent":25,"growth_sowing":0.0013,"growth_vegetative":0.3988,"growth_flowering":0.5323,"growth_maturity":0.0676,"disturbance_none":0.095,"disturbance_weeds":0.7824,"disturbance_drought":0.1223,"disturbance_nutrient_deficit":0.0003,"crop_name":"maize","spatial_location":"Mbeere-South"}]
