[{"farmer_unique_id":"EM1345","site_id":6960,"date":"2021-04-18 09:24:30","filename":"L134F04131C01S06960Rp15529.jpg","season":"LR2021","growth_stage":"V","damage":"WD","extent":30,"drought_probability":0.4062,"drought_extent":31,"growth_sowing":0.0071,"growth_vegetative":0.7975,"growth_flowering":0.1666,"growth_maturity":0.0288,"disturbance_none":0.0196,"disturbance_weeds":0.891,"disturbance_drought":0.0859,"disturbance_nutrient_deficit":0.0034,"crop_name":"maize","spatial_location":"Mbeere-South"}]
