[{"farmer_unique_id":"1348916450","site_id":9793,"date":"2021-07-03 07:41:04","filename":"L134F00871C01S09793Rp29236.jpg","season":"LR2021","growth_stage":"M","damage":"DR","extent":40,"drought_probability":0.1788,"drought_extent":38,"growth_sowing":0.0021,"growth_vegetative":0.3419,"growth_flowering":0.3298,"growth_maturity":0.3263,"disturbance_none":0.0338,"disturbance_weeds":0.9254,"disturbance_drought":0.0406,"disturbance_nutrient_deficit":0.0002,"crop_name":"maize","spatial_location":"Mbeere-South"}]
