[{"farmer_unique_id":"EM1343","site_id":7410,"date":"2021-07-03 07:03:30","filename":"L134F00091C01S07410Rp29217.jpg","season":"LR2021","growth_stage":"M","damage":"G","extent":0,"drought_probability":0.4619,"drought_extent":-0,"growth_sowing":0.0003,"growth_vegetative":0.0004,"growth_flowering":0.2463,"growth_maturity":0.753,"disturbance_none":0.005,"disturbance_weeds":0.953,"disturbance_drought":0.0401,"disturbance_nutrient_deficit":0.0018,"crop_name":"maize","spatial_location":"Mbeere-South"}]
