[{"farmer_unique_id":"1349558343","site_id":6932,"date":"2021-07-21 10:34:45","filename":"L134F00875C01S06932Rp31365.jpg","season":"LR2021","growth_stage":"M","damage":"DR","extent":40,"drought_probability":0.9839,"drought_extent":98,"growth_sowing":8.707e-07,"growth_vegetative":0,"growth_flowering":0.007,"growth_maturity":0.993,"disturbance_none":0.0002,"disturbance_weeds":0.0025,"disturbance_drought":0.9971,"disturbance_nutrient_deficit":0.0003,"crop_name":"maize","spatial_location":"Mbeere-South"}]
