[{"farmer_unique_id":"1344106610","site_id":9684,"date":"2021-06-18 07:02:35","filename":"L134F00805C01S09684Rp25701.jpg","season":"LR2021","growth_stage":"M","damage":"DR","extent":40,"drought_probability":0.6409,"drought_extent":56,"growth_sowing":0,"growth_vegetative":0.0007,"growth_flowering":0.1494,"growth_maturity":0.8498,"disturbance_none":0.0046,"disturbance_weeds":0.2935,"disturbance_drought":0.5324,"disturbance_nutrient_deficit":0.1695,"crop_name":"maize","spatial_location":"Mbeere-South"}]
