[{"farmer_unique_id":"1342922799","site_id":7237,"date":"2021-04-12 17:36:46","filename":"L134F00787C01S07237Rp15182.jpg","season":"LR2021","growth_stage":"S","damage":"WD","extent":30,"drought_probability":0.1879,"drought_extent":44,"growth_sowing":0.4974,"growth_vegetative":0.4649,"growth_flowering":0.0042,"growth_maturity":0.0335,"disturbance_none":0.0712,"disturbance_weeds":0.9257,"disturbance_drought":0.0031,"disturbance_nutrient_deficit":1.1624e-06,"crop_name":"maize","spatial_location":"Mbeere-South"}]
