[{"farmer_unique_id":"1340367274","site_id":10511,"date":"2021-06-19 09:13:25","filename":"L134F00755C01S10511Rp26098.jpg","season":"LR2021","growth_stage":"M","damage":"DR","extent":40,"drought_probability":0.9161,"drought_extent":54,"growth_sowing":0,"growth_vegetative":0.0002,"growth_flowering":0.3108,"growth_maturity":0.689,"disturbance_none":0.0206,"disturbance_weeds":0.1761,"disturbance_drought":0.7959,"disturbance_nutrient_deficit":0.0074,"crop_name":"maize","spatial_location":"Mbeere-South"}]
