[{"farmer_unique_id":"4365370","site_id":9159,"date":"2021-07-15 09:11:22","filename":"L141F03044C01S09159Rp30764.jpg","season":"LR2021","growth_stage":"M","damage":"DR","extent":40,"drought_probability":0.9849,"drought_extent":71,"growth_sowing":9.0866e-06,"growth_vegetative":0,"growth_flowering":0.0015,"growth_maturity":0.9985,"disturbance_none":0.0004,"disturbance_weeds":0.0013,"disturbance_drought":0.9978,"disturbance_nutrient_deficit":0.0005,"crop_name":"maize","spatial_location":"Mbeere-North"}]
