[{"farmer_unique_id":"4761279","site_id":7031,"date":"2021-05-26 08:56:51","filename":"L141F03315C01S07031Rp21357.jpg","season":"LR2021","growth_stage":"F","damage":"WD","extent":40,"drought_probability":0.0005,"drought_extent":-0,"growth_sowing":0,"growth_vegetative":0.0116,"growth_flowering":0.5893,"growth_maturity":0.3991,"disturbance_none":0.7242,"disturbance_weeds":0.2758,"disturbance_drought":0,"disturbance_nutrient_deficit":1.085e-06,"crop_name":"maize","spatial_location":"Mbeere-North"}]
