[{"farmer_unique_id":"1446054","site_id":7461,"date":"2021-04-29 11:02:56","filename":"L144F00937C01S07461Rp16601.jpg","season":"LR2021","growth_stage":"V","damage":"WD","extent":30,"drought_probability":0.0263,"drought_extent":1,"growth_sowing":0.0011,"growth_vegetative":0.9947,"growth_flowering":0.0039,"growth_maturity":0.0002,"disturbance_none":0.0113,"disturbance_weeds":0.9783,"disturbance_drought":0.0103,"disturbance_nutrient_deficit":0.0001,"crop_name":"maize","spatial_location":"Mbeere-North"}]
