[{"farmer_unique_id":"1792756","site_id":8579,"date":"2021-05-22 08:56:48","filename":"L144F01122C01S08579Rp20631.jpg","season":"LR2021","growth_stage":"V","damage":"WD","extent":30,"drought_probability":0.0023,"drought_extent":5,"growth_sowing":0.0001,"growth_vegetative":0.0033,"growth_flowering":0.9701,"growth_maturity":0.0265,"disturbance_none":0.2839,"disturbance_weeds":0.7148,"disturbance_drought":0.0012,"disturbance_nutrient_deficit":0.0001,"crop_name":"maize","spatial_location":"Mbeere-North"}]
