[{"farmer_unique_id":"TN2312","site_id":6804,"date":"2021-06-18 07:07:11","filename":"L231F00243C02S06804Rp25707.jpg","season":"LR2021","growth_stage":"M","damage":"DR","extent":60,"drought_probability":0.8662,"drought_extent":51,"growth_sowing":0.0037,"growth_vegetative":0.0155,"growth_flowering":0.0171,"growth_maturity":0.9636,"disturbance_none":0.0096,"disturbance_weeds":0.0347,"disturbance_drought":0.9545,"disturbance_nutrient_deficit":0.0012,"crop_name":"sorghum","spatial_location":"Igembe-South"}]
