[{"farmer_unique_id":"3654450","site_id":7603,"date":"2021-05-07 17:23:09","filename":"L231F02385C03S07603Rp17805.jpg","season":"LR2021","growth_stage":"V","damage":"WD","extent":10,"drought_probability":0.0109,"drought_extent":19,"growth_sowing":0.17,"growth_vegetative":0.8016,"growth_flowering":0.0162,"growth_maturity":0.0122,"disturbance_none":0.0481,"disturbance_weeds":0.9378,"disturbance_drought":0.0139,"disturbance_nutrient_deficit":0.0002,"crop_name":"green gram","spatial_location":"Tharaka"}]
