[{"farmer_unique_id":"ME3212","site_id":7028,"date":"2021-06-23 14:32:03","filename":"L321F03728C01S07028Rp26973.jpg","season":"LR2021","growth_stage":"M","damage":"DR","extent":10,"drought_probability":0.0887,"drought_extent":3,"growth_sowing":0.0006,"growth_vegetative":0.0026,"growth_flowering":0.3791,"growth_maturity":0.6176,"disturbance_none":0.1731,"disturbance_weeds":0.2419,"disturbance_drought":0.4869,"disturbance_nutrient_deficit":0.0981,"crop_name":"maize","spatial_location":"Tigania-West"}]
