[{"farmer_unique_id":"ME3261","site_id":6977,"date":"2021-07-12 15:53:36","filename":"L326F00156C01S06977Rp30390.jpg","season":"LR2021","growth_stage":"F","damage":"DR","extent":60,"drought_probability":0.3274,"drought_extent":0,"growth_sowing":0.8285,"growth_vegetative":0.0135,"growth_flowering":0.0038,"growth_maturity":0.1541,"disturbance_none":0.0587,"disturbance_weeds":0.1192,"disturbance_drought":0.8194,"disturbance_nutrient_deficit":0.0028,"crop_name":"maize","spatial_location":"Tigania-West"}]
