[{"farmer_unique_id":"ME3314","site_id":7065,"date":"2021-07-04 16:55:14","filename":"L331F00160C01S07065Rp29489.jpg","season":"LR2021","growth_stage":"F","damage":"G","extent":0,"drought_probability":0.0086,"drought_extent":7,"growth_sowing":0.0002,"growth_vegetative":0.1395,"growth_flowering":0.8502,"growth_maturity":0.0101,"disturbance_none":0.9001,"disturbance_weeds":0.0988,"disturbance_drought":0.0008,"disturbance_nutrient_deficit":0.0003,"crop_name":"maize","spatial_location":"Central-Imenti"}]
