[{"farmer_unique_id":"ME3321","site_id":9100,"date":"2021-06-13 14:33:22","filename":"L332F00162C01S09100Rp24595.jpg","season":"LR2021","growth_stage":"F","damage":"DR","extent":30,"drought_probability":0.0746,"drought_extent":7,"growth_sowing":0,"growth_vegetative":0.0012,"growth_flowering":0.9498,"growth_maturity":0.049,"disturbance_none":0.1967,"disturbance_weeds":0.2259,"disturbance_drought":0.5739,"disturbance_nutrient_deficit":0.0035,"crop_name":"maize","spatial_location":"Central-Imenti"}]
