[{"farmer_unique_id":"2147790","site_id":6868,"date":"2021-05-10 13:13:37","filename":"L341F01307C01S06868Rp18358.jpg","season":"LR2021","growth_stage":"V","damage":"WD","extent":30,"drought_probability":0.0001,"drought_extent":0,"growth_sowing":7.6096e-07,"growth_vegetative":0.0209,"growth_flowering":0.9756,"growth_maturity":0.0035,"disturbance_none":0.9891,"disturbance_weeds":0.0105,"disturbance_drought":0.0004,"disturbance_nutrient_deficit":2.1665e-07,"crop_name":"maize","spatial_location":"South-Imenti"}]
