[{"farmer_unique_id":"4016369","site_id":8079,"date":"2021-06-11 12:24:33","filename":"L341F02738C01S08079Rp24276.jpg","season":"LR2021","growth_stage":"M","damage":"G","extent":0,"drought_probability":0.1903,"drought_extent":10,"growth_sowing":0.0005,"growth_vegetative":0.0003,"growth_flowering":0.4038,"growth_maturity":0.5953,"disturbance_none":0.3172,"disturbance_weeds":0.1733,"disturbance_drought":0.5091,"disturbance_nutrient_deficit":0.0004,"crop_name":"maize","spatial_location":"South-Imenti"}]
