[{"farmer_unique_id":"2229594","site_id":6852,"date":"2021-05-10 12:54:59","filename":"L341F01343C01S06852Rp18334.jpg","season":"LR2021","growth_stage":"V","damage":"WD","extent":30,"drought_probability":1.2665e-06,"drought_extent":1,"growth_sowing":6.2568e-08,"growth_vegetative":0.9997,"growth_flowering":0.0002,"growth_maturity":0,"disturbance_none":0.9938,"disturbance_weeds":0.0062,"disturbance_drought":0.0001,"disturbance_nutrient_deficit":3.5006e-06,"crop_name":"maize","spatial_location":"South-Imenti"}]
