[{"farmer_unique_id":"4282221","site_id":8865,"date":"2021-06-30 08:22:46","filename":"L354F03995C01S08865Rp28644.jpg","season":"LR2021","growth_stage":"F","damage":"DR","extent":40,"drought_probability":0.8848,"drought_extent":28,"growth_sowing":9.8296e-06,"growth_vegetative":0.0002,"growth_flowering":0.0064,"growth_maturity":0.9934,"disturbance_none":0.0002,"disturbance_weeds":0.0025,"disturbance_drought":0.9873,"disturbance_nutrient_deficit":0.0099,"crop_name":"maize","spatial_location":"Tigania-East"}]
