[{"farmer_unique_id":"3553143","site_id":8910,"date":"2021-05-18 16:03:30","filename":"L355F02282C02S08910Rp30558.jpg","season":"LR2021","growth_stage":"V","damage":"WD","extent":20,"drought_probability":0.0192,"drought_extent":14,"growth_sowing":0.0053,"growth_vegetative":0.8273,"growth_flowering":0.139,"growth_maturity":0.0284,"disturbance_none":0.0306,"disturbance_weeds":0.962,"disturbance_drought":0.0069,"disturbance_nutrient_deficit":0.0005,"crop_name":"sorghum","spatial_location":"Tigania-East"}]
