[{"farmer_unique_id":"3611101","site_id":10020,"date":"2021-06-26 13:53:55","filename":"L361F02349C01S10020Rp27927.jpg","season":"LR2021","growth_stage":"V","damage":"G","extent":0,"drought_probability":0.4126,"drought_extent":28,"growth_sowing":0.0002,"growth_vegetative":0.0009,"growth_flowering":0.1563,"growth_maturity":0.8426,"disturbance_none":0.0241,"disturbance_weeds":0.1088,"disturbance_drought":0.6793,"disturbance_nutrient_deficit":0.1878,"crop_name":"maize","spatial_location":"North-Imenti"}]
