[{"farmer_unique_id":"425820488","site_id":9542,"date":"2021-05-28 11:20:23","filename":"L371F04478C01S09542Rp21833.jpg","season":"LR2021","growth_stage":"V","damage":"WD","extent":70,"drought_probability":0.0083,"drought_extent":6,"growth_sowing":0.0001,"growth_vegetative":0.7972,"growth_flowering":0.2014,"growth_maturity":0.0013,"disturbance_none":0.0179,"disturbance_weeds":0.982,"disturbance_drought":0.0001,"disturbance_nutrient_deficit":0.0001,"crop_name":"maize","spatial_location":"Masinga"}]
