[{"farmer_unique_id":"3065218","site_id":9636,"date":"2021-06-28 13:33:56","filename":"L371F01852C01S09636Rp28330.jpg","season":"LR2021","growth_stage":"F","damage":"DR","extent":30,"drought_probability":0.0367,"drought_extent":11,"growth_sowing":0.0001,"growth_vegetative":0.0002,"growth_flowering":0.346,"growth_maturity":0.6538,"disturbance_none":0.7752,"disturbance_weeds":0.1928,"disturbance_drought":0.0211,"disturbance_nutrient_deficit":0.0108,"crop_name":"maize","spatial_location":"Masinga"}]
