[{"farmer_unique_id":"3960653","site_id":7293,"date":"2021-06-25 10:09:06","filename":"L410F02693C01S07293Rp27527.jpg","season":"LR2021","growth_stage":"F","damage":"DR","extent":50,"drought_probability":0.7809,"drought_extent":7,"growth_sowing":0.0004,"growth_vegetative":0.0005,"growth_flowering":0.2845,"growth_maturity":0.7146,"disturbance_none":0.0303,"disturbance_weeds":0.0841,"disturbance_drought":0.8828,"disturbance_nutrient_deficit":0.0028,"crop_name":"maize","spatial_location":"Mwala"}]
