[{"farmer_unique_id":"428040158","site_id":10354,"date":"2021-06-04 10:17:41","filename":"L428F04484C01S10354Rp23063.jpg","season":"LR2021","growth_stage":"V","damage":"G","extent":0,"drought_probability":0.5466,"drought_extent":33,"growth_sowing":0.0004,"growth_vegetative":0.956,"growth_flowering":0.0392,"growth_maturity":0.0044,"disturbance_none":0.0273,"disturbance_weeds":0.1035,"disturbance_drought":0.8559,"disturbance_nutrient_deficit":0.0133,"crop_name":"maize","spatial_location":"Makueni"}]
