[{"farmer_unique_id":"1708971","site_id":7669,"date":"2021-06-27 14:37:00","filename":"L433F01088C01S07669Rp28102.jpg","season":"LR2021","growth_stage":"V","damage":"DR","extent":50,"drought_probability":0.1417,"drought_extent":3,"growth_sowing":0.0012,"growth_vegetative":0.0127,"growth_flowering":0.7167,"growth_maturity":0.2694,"disturbance_none":0.0274,"disturbance_weeds":0.9551,"disturbance_drought":0.0161,"disturbance_nutrient_deficit":0.0014,"crop_name":"maize","spatial_location":"Kibwezi-West"}]
