[{"farmer_unique_id":"94983","site_id":7386,"date":"2021-06-23 11:23:04","filename":"L435F00277C01S07386Rp26908.jpg","season":"LR2021","growth_stage":"S","damage":"G","extent":0,"drought_probability":0.4063,"drought_extent":1,"growth_sowing":0.9209,"growth_vegetative":0.0784,"growth_flowering":0.0003,"growth_maturity":0.0004,"disturbance_none":0.269,"disturbance_weeds":0.5896,"disturbance_drought":0.1413,"disturbance_nutrient_deficit":0.0001,"crop_name":"maize","spatial_location":"Kibwezi-West"}]
